LICENSE
README.md
setup.py
Evaltest/__init__.py
Evaltest/chunk_it.py
Evaltest/clean_it.py
Evaltest/extractor.py
Evaltest/get_evaluation_question.py
Evaltest/prag.py
Evaltest/trulens.py
Evaltest/utils.py
Evaltest.egg-info/PKG-INFO
Evaltest.egg-info/SOURCES.txt
Evaltest.egg-info/dependency_links.txt
Evaltest.egg-info/requires.txt
Evaltest.egg-info/top_level.txt