Metadata-Version: 2.1
Name: Evaltest
Version: 0.0.1.31
Summary: This library is to search the best parameters across different steps of the RAG process.
Home-page: https://github.com/hidevscommunity/gen-ai-library/tree/main/Ankit
Author: Ankit
Author-email: a.baliyan008@gmail.com
License: MIT
License-File: LICENSE
